[{"status_code":200,"operation_id":"batchtest1","response":"{\"lists\":[{\"id\":\"4cbb0e032a\",\"web_id\":704369,\"name\":\"Rich's Real Test list\",\"contact\":{\"company\":\"Artful Robot\",\"address1\":\"64 Wilkins Road\",\"address2\":\"\",\"city\":\"Oxford\",\"state\":\"\",\"zip\":\"ox4 2hz\",\"country\":\"GB\",\"phone\":\"\"},\"permission_reminder\":\"This is for testing.\",\"use_archive_bar\":true,\"campaign_defaults\":{\"from_name\":\"Rich Lott\",\"from_email\":\"forums@artfulrobot.uk\",\"subject\":\"\",\"language\":\"en\"},\"notify_on_subscribe\":\"\",\"notify_on_unsubscribe\":\"\",\"date_created\":\"2016-05-27T15:54:32+00:00\",\"list_rating\":0,\"email_type_option\":false,\"subscribe_url_short\":\"http:\/\/eepurl.com\/b3t1E1\",\"subscribe_url_long\":\"https:\/\/artfulrobot.us9.list-manage.com\/subscribe?u=23ec89b2617651c7667fd3ee6&id=4cbb0e032a\",\"beamer_address\":\"us9-316b17c388-3b6d01127c@inbound.mailchimp.com\",\"visibility\":\"pub\",\"double_optin\":false,\"has_welcome\":false,\"marketing_permissions\":false,\"modules\":[],\"stats\":{\"member_count\":4,\"unsubscribe_count\":3,\"cleaned_count\":0,\"member_count_since_send\":0,\"unsubscribe_count_since_send\":1,\"cleaned_count_since_send\":0,\"campaign_count\":3,\"campaign_last_sent\":\"\",\"merge_field_count\":6,\"avg_sub_rate\":0,\"avg_unsub_rate\":0,\"target_sub_rate\":0,\"open_rate\":100,\"click_rate\":0,\"last_sub_date\":\"2019-06-19T10:49:28+00:00\",\"last_unsub_date\":\"2019-09-04T11:27:39+00:00\"},\"_links\":[{\"rel\":\"self\",\"href\":\"https:\/\/us9.api.mailchimp.com\/3.0\/lists\/4cbb0e032a\",\"method\":\"GET\",\"targetSchema\":\"https:\/\/us9.api.mailchimp.com\/schema\/3.0\/Definitions\/Lists\/Response.json\"},{\"rel\":\"parent\",\"href\":\"https:\/\/us9.api.mailchimp.com\/3.0\/lists\",\"method\":\"GET\",\"targetSchema\":\"https:\/\/us9.api.mailchimp.com\/schema\/3.0\/Definitions\/Lists\/CollectionResponse.json\",\"schema\":\"https:\/\/us9.api.mailchimp.com\/schema\/3.0\/CollectionLinks\/Lists.json\"},{\"rel\":\"update\",\"href\":\"https:\/\/us9.api.mailchimp.com\/3.0\/lists\/4cbb0e032a\",\"method\":\"PATCH\",\"targetSchema\":\"https:\/\/us9.api.mailchimp.com\/schema\/3.0\/Definitions\/Lists\/Response.json\",\"schema\":\"https:\/\/us9.api.mailchimp.com\/schema\/3.0\/Definitions\/Lists\/PATCH.json\"},{\"rel\":\"batch-sub-unsub-members\",\"href\":\"https:\/\/us9.api.mailchimp.com\/3.0\/lists\/4cbb0e032a\",\"method\":\"POST\",\"targetSchema\":\"https:\/\/us9.api.mailchimp.com\/schema\/3.0\/Definitions\/Lists\/BatchPOST-Response.json\",\"schema\":\"https:\/\/us9.api.mailchimp.com\/schema\/3.0\/Definitions\/Lists\/BatchPOST.json\"},{\"rel\":\"delete\",\"href\":\"https:\/\/us9.api.mailchimp.com\/3.0\/lists\/4cbb0e032a\",\"method\":\"DELETE\"},{\"rel\":\"abuse-reports\",\"href\":\"https:\/\/us9.api.mailchimp.com\/3.0\/lists\/4cbb0e032a\/abuse-reports\",\"method\":\"GET\",\"targetSchema\":\"https:\/\/us9.api.mailchimp.com\/schema\/3.0\/Definitions\/Lists\/Abuse\/CollectionResponse.json\",\"schema\":\"https:\/\/us9.api.mailchimp.com\/schema\/3.0\/CollectionLinks\/Lists\/Abuse.json\"},{\"rel\":\"activity\",\"href\":\"https:\/\/us9.api.mailchimp.com\/3.0\/lists\/4cbb0e032a\/activity\",\"method\":\"GET\",\"targetSchema\":\"https:\/\/us9.api.mailchimp.com\/schema\/3.0\/Definitions\/Lists\/Activity\/Response.json\"},{\"rel\":\"clients\",\"href\":\"https:\/\/us9.api.mailchimp.com\/3.0\/lists\/4cbb0e032a\/clients\",\"method\":\"GET\",\"targetSchema\":\"https:\/\/us9.api.mailchimp.com\/schema\/3.0\/Definitions\/Lists\/Clients\/Response.json\"},{\"rel\":\"growth-history\",\"href\":\"https:\/\/us9.api.mailchimp.com\/3.0\/lists\/4cbb0e032a\/growth-history\",\"method\":\"GET\",\"targetSchema\":\"https:\/\/us9.api.mailchimp.com\/schema\/3.0\/Definitions\/Lists\/Growth\/CollectionResponse.json\",\"schema\":\"https:\/\/us9.api.mailchimp.com\/schema\/3.0\/CollectionLinks\/Lists\/Growth.json\"},{\"rel\":\"interest-categories\",\"href\":\"https:\/\/us9.api.mailchimp.com\/3.0\/lists\/4cbb0e032a\/interest-categories\",\"method\":\"GET\",\"targetSchema\":\"https:\/\/us9.api.mailchimp.com\/schema\/3.0\/Definitions\/Lists\/InterestCategories\/CollectionResponse.json\",\"schema\":\"https:\/\/us9.api.mailchimp.com\/schema\/3.0\/CollectionLinks\/Lists\/InterestCategories.json\"},{\"rel\":\"members\",\"href\":\"https:\/\/us9.api.mailchimp.com\/3.0\/lists\/4cbb0e032a\/members\",\"method\":\"GET\",\"targetSchema\":\"https:\/\/us9.api.mailchimp.com\/schema\/3.0\/Definitions\/Lists\/Members\/CollectionResponse.json\",\"schema\":\"https:\/\/us9.api.mailchimp.com\/schema\/3.0\/CollectionLinks\/Lists\/Members.json\"},{\"rel\":\"merge-fields\",\"href\":\"https:\/\/us9.api.mailchimp.com\/3.0\/lists\/4cbb0e032a\/merge-fields\",\"method\":\"GET\",\"targetSchema\":\"https:\/\/us9.api.mailchimp.com\/schema\/3.0\/Definitions\/Lists\/MergeFields\/CollectionResponse.json\",\"schema\":\"https:\/\/us9.api.mailchimp.com\/schema\/3.0\/CollectionLinks\/Lists\/MergeFields.json\"},{\"rel\":\"segments\",\"href\":\"https:\/\/us9.api.mailchimp.com\/3.0\/lists\/4cbb0e032a\/segments\",\"method\":\"GET\",\"targetSchema\":\"https:\/\/us9.api.mailchimp.com\/schema\/3.0\/Definitions\/Lists\/Segments\/CollectionResponse.json\",\"schema\":\"https:\/\/us9.api.mailchimp.com\/schema\/3.0\/CollectionLinks\/Lists\/Segments.json\"},{\"rel\":\"webhooks\",\"href\":\"https:\/\/us9.api.mailchimp.com\/3.0\/lists\/4cbb0e032a\/webhooks\",\"method\":\"GET\",\"targetSchema\":\"https:\/\/us9.api.mailchimp.com\/schema\/3.0\/Definitions\/Lists\/Webhooks\/CollectionResponse.json\",\"schema\":\"https:\/\/us9.api.mailchimp.com\/schema\/3.0\/CollectionLinks\/Lists\/Webhooks.json\"},{\"rel\":\"signup-forms\",\"href\":\"https:\/\/us9.api.mailchimp.com\/3.0\/lists\/4cbb0e032a\/signup-forms\",\"method\":\"GET\",\"targetSchema\":\"https:\/\/us9.api.mailchimp.com\/schema\/3.0\/Definitions\/Lists\/SignupForms\/CollectionResponse.json\",\"schema\":\"https:\/\/us9.api.mailchimp.com\/schema\/3.0\/CollectionLinks\/Lists\/SignupForms.json\"},{\"rel\":\"locations\",\"href\":\"https:\/\/us9.api.mailchimp.com\/3.0\/lists\/4cbb0e032a\/locations\",\"method\":\"GET\",\"targetSchema\":\"https:\/\/us9.api.mailchimp.com\/schema\/3.0\/Definitions\/Lists\/Locations\/CollectionResponse.json\",\"schema\":\"https:\/\/us9.api.mailchimp.com\/schema\/3.0\/CollectionLinks\/Lists\/Locations.json\"}]}],\"total_items\":1,\"constraints\":{\"may_create\":false,\"max_instances\":1,\"current_total_instances\":1},\"_links\":[{\"rel\":\"self\",\"href\":\"https:\/\/us9.api.mailchimp.com\/3.0\/lists\",\"method\":\"GET\",\"targetSchema\":\"https:\/\/us9.api.mailchimp.com\/schema\/3.0\/Definitions\/Lists\/CollectionResponse.json\",\"schema\":\"https:\/\/us9.api.mailchimp.com\/schema\/3.0\/CollectionLinks\/Lists.json\"},{\"rel\":\"parent\",\"href\":\"https:\/\/us9.api.mailchimp.com\/3.0\/\",\"method\":\"GET\",\"targetSchema\":\"https:\/\/us9.api.mailchimp.com\/schema\/3.0\/Definitions\/Root\/Response.json\"},{\"rel\":\"create\",\"href\":\"https:\/\/us9.api.mailchimp.com\/3.0\/lists\",\"method\":\"POST\",\"targetSchema\":\"https:\/\/us9.api.mailchimp.com\/schema\/3.0\/Definitions\/Lists\/Response.json\",\"schema\":\"https:\/\/us9.api.mailchimp.com\/schema\/3.0\/Definitions\/Lists\/POST.json\"}],\"returned_item_count\":1}"}]